flask_pusher.py
Flask_Pusher-2.0.2.dist-info/METADATA
Flask_Pusher-2.0.2.dist-info/RECORD
Flask_Pusher-2.0.2.dist-info/WHEEL
Flask_Pusher-2.0.2.dist-info/top_level.txt
