Metadata-Version: 2.1
Name: Flask-Pusher
Version: 2.0.2
Summary: Flask extension for Pusher
Home-page: https://www.github.com/iurisilvio/Flask-Pusher
Author: Iuri de Silvio
Author-email: iurisilvio@gmail.com
License: MIT
Platform: any
Classifier: Environment :: Web Environment
Classifier: Intended Audience :: Developers
Classifier: License :: OSI Approved :: MIT License
Classifier: Operating System :: OS Independent
Classifier: Programming Language :: Python
Classifier: Topic :: Internet :: WWW/HTTP :: Dynamic Content
Classifier: Topic :: Software Development :: Libraries :: Python Modules
Requires-Dist: Flask
Requires-Dist: pusher (<3)
Requires-Dist: Flask-Jsonpify
